pylicensemanager/__init__.py
pylicensemanager/internal.py
pylicensemanager/main.py
pylicensemanager/methods.py
pylicensemanager/models.py
pylicensemanager-0.1.5.dist-info/WHEEL
pylicensemanager-0.1.5.dist-info/METADATA
pylicensemanager-0.1.5.dist-info/RECORD
